capisce/__init__.py
capisce/req.py
capisce/wsgi.py
capisce/templates/index.html
capisce/templates/assets/bootstrap/css/bootstrap.min.css
capisce/templates/assets/bootstrap/js/bootstrap.min.js
capisce/templates/assets/css/styles.min.css
capisce/templates/assets/img/16.png
capisce/templates/assets/img/180.png
capisce/templates/assets/img/192.png
capisce/templates/assets/img/32.png
capisce/templates/assets/img/512.png
capisce/templates/assets/img/exclude.svg
capisce/templates/assets/js/jquery.min.js
capisce/templates/assets/js/script.min.js
capisce/templates/assets/json/db.json
capisce-0.1.7.dist-info/LICENSE
capisce-0.1.7.dist-info/METADATA
capisce-0.1.7.dist-info/WHEEL
capisce-0.1.7.dist-info/entry_points.txt
capisce-0.1.7.dist-info/top_level.txt
capisce-0.1.7.dist-info/RECORD
