Metadata-Version: 2.1
Name: capisce
Version: 0.1.7
Summary: The Open-Source API Testing Tool
Author-email: Kaan Giray Buzluk <kaangiray26@protonmail.com>
License: GNU GENERAL PUBLIC LICENSE
Project-URL: Homepage, https://github.com/kaangiray26/capisce
Project-URL: Bug Tracker, https://github.com/kaangiray26/capisce/issues
Classifier: Programming Language :: Python :: 3
Classifier: License :: OSI Approved :: GNU General Public License v3 (GPLv3)
Classifier: Operating System :: OS Independent
Requires-Python: >=3.7
License-File: LICENSE
Requires-Dist: requests
Requires-Dist: Flask
Requires-Dist: ratelimit
Requires-Dist: flask-cors
